{
  "name": "Homepage",
  "fields":{
		"welcome": {
			"title": "Welcome",
			"type": "section",
			"items": {
				"title": {
					"title": "Title",
					"type": "text"
				},
				"content": {
					"title": "Content",
					"type": "wysiwyg"
				}
			}
		},
    "content": {
      "title": "Content",
      "type": "section",
      "items": {
        "sections": {
          "title": "Sections",
    			"type": "repeater",
    			"items": {
    				"title": {
    					"title": "Title",
    					"type": "text"
    				},
    				"content": {
    					"title": "Content",
    					"type": "wysiwyg"
    				}
    			}
        }
  		}
    },
    "floors": {
      "title": "Floors",
      "type": "section",
      "items": {
        "links": {
          "title": "Links",
          "type": "repeater",
          "items": {
            "empty": {
              "title": "Empty?",
              "type": "boolean"
            },
            "url": {
							"title": "URL",
							"type": "text"
						},
            "title": {
							"title": "Title",
							"type": "text"
						},
            "floor": {
              "title": "Floor",
              "type": "text"
            },
            "img": {
              "title": "Hover Image",
              "type": "image"
            }
          }
        }
      }
    },
		"crownshy": {
			"title": "Crown Shy",
			"type": "section",
			"items": {
				"link": {
					"title": "Link",
					"type": "section",
					"items": {
						"url": {
							"title": "URL",
							"type": "text"
						},
						"title": {
							"title": "Title",
							"type": "text"
						},
						"target": {
							"title": "Open link in new tab?",
							"type": "boolean"
						}
					}
				},
				"content": {
					"title": "Hover Copy",
					"type": "text"
				},
				"logo": {
					"title": "Logo",
					"type": "image"
				}
			}
		}
  },
  "wireframe": [
    "section-welcome",
    "section-content",
    "section-floors",
    "section-crownshy"
  ]
}
